{
  "created": 1774946548,
  "data": [
    {
      "url": "https://p16-dreamina-sign-sg.ibyteimg.com/tos-alisg-i-wopfjsm1ax-sg/d545c97ffddd4ce1bbb0f0f845f59944~tplv-wopfjsm1ax-aigc_resize:0:0.jpeg?lk3s=43402efa&x-expires=1776816000&x-signature=L1twx%2FT0gyiurnx3CE2bO6nr58g%3D&format=.jpeg"
    },
    {
      "url": "https://p16-dreamina-sign-sg.ibyteimg.com/tos-alisg-i-wopfjsm1ax-sg/61f1ff2842e649548bfd0f0aa2e4f21f~tplv-wopfjsm1ax-aigc_resize:0:0.jpeg?lk3s=43402efa&x-expires=1776816000&x-signature=TMfCbbE0svihkbW%2FRxfqW%2FuMVeo%3D&format=.jpeg"
    },
    {
      "url": "https://p16-dreamina-sign-sg.ibyteimg.com/tos-alisg-i-wopfjsm1ax-sg/2082f5599ba746f8b8b5dd1829fd8988~tplv-wopfjsm1ax-aigc_resize:0:0.jpeg?lk3s=43402efa&x-expires=1776816000&x-signature=%2FyXtqMpg9gqIwXa8r23PUExNqxQ%3D&format=.jpeg"
    },
    {
      "url": "https://p16-dreamina-sign-sg.ibyteimg.com/tos-alisg-i-wopfjsm1ax-sg/bc8febe4dd3c41099542d3ee6f84c013~tplv-wopfjsm1ax-aigc_resize:0:0.jpeg?lk3s=43402efa&x-expires=1776816000&x-signature=xfZPqheWDvOY9Yr%2BEqnIk6PLuyE%3D&format=.jpeg"
    }
  ]
}
