[
  {
    "query": "Japan election rally crowd Tokyo 4k",
    "candidates": [
      {
        "title": "Crowds line Tokyo streets to mourn former Prime Minister Shinzo Abe",
        "url": "https://www.youtube.com/watch?v=BsZ6TPY3fpU",
        "duration": 19.0,
        "channel": "6abc Philadelphia"
      },
      {
        "title": "Tokyo Harajuku Street Protest",
        "url": "https://www.youtube.com/watch?v=KvVH-8CZ9g4",
        "duration": 30.0,
        "channel": "Derrick Lin"
      },
      {
        "title": "Professional Pushers Shove Passengers Onto Busy Tokyo Train",
        "url": "https://www.youtube.com/watch?v=o9Xg7ui5mLA",
        "duration": 46.0,
        "channel": "ABC News"
      }
    ]
  },
  {
    "query": "Japanese parliament diet building b roll",
    "candidates": [
      {
        "title": "Inside Japan’s National Diet Building: A Rare Tour of Tokyo’s Parliament",
        "url": "https://www.youtube.com/watch?v=Mr7YAO14cKg",
        "duration": 122.0,
        "channel": "travelformortals"
      },
      {
        "title": "B-roll: National Day of Remembance",
        "url": "https://www.youtube.com/watch?v=6IBoS96ZY64",
        "duration": 45.0,
        "channel": "Dick Hughes"
      },
      {
        "title": "Trump stops to retrieve Marine's hat",
        "url": "https://www.youtube.com/watch?v=pAbgc41pksE",
        "duration": 36.0,
        "channel": "CNN"
      }
    ]
  },
  {
    "query": "Tokyo crowd crossing 4k documentary",
    "candidates": [
      {
        "title": "The famous Shibuya crossing - 90 seconds",
        "url": "https://www.youtube.com/watch?v=Od6EeCWytZo",
        "duration": 108.0,
        "channel": "Carl Rosa"
      },
      {
        "title": "Tokyo: A City That Feels Like Another Planet",
        "url": "https://www.youtube.com/watch?v=BhBcICoRY6Q",
        "duration": 2849.0,
        "channel": "CoolVision"
      },
      {
        "title": "Shinjuku, Tokyo | M6.1 Japan Earthquake",
        "url": "https://www.youtube.com/watch?v=1r_XiQhaSr4",
        "duration": 21.0,
        "channel": "HUCN Explores"
      }
    ]
  },
  {
    "query": "Japan military drill coast guard 4k",
    "candidates": [
      {
        "title": "Japan-U.S.  joint drill held at Yokosuka Port",
        "url": "https://www.youtube.com/watch?v=PcmQWsTH9OM",
        "duration": 35.0,
        "channel": "Nippon Television News Japan"
      },
      {
        "title": "China Coast Guard Vessels Near Japan's Senkaku Island, Xi Sends Jets, Warships To Rattle Taiwan | 4K",
        "url": "https://www.youtube.com/watch?v=PAzJYKB6tvA",
        "duration": 488.0,
        "channel": "CRUX"
      },
      {
        "title": "Japan coast guard ship arrives in Da Nang",
        "url": "https://www.youtube.com/watch?v=5ollpsDyzew",
        "duration": 44.0,
        "channel": "Vietnam News Agency (VNA)"
      }
    ]
  },
  {
    "query": "Japan aging society elderly crowd street 4k",
    "candidates": [
      {
        "title": "Japan's elderly citizens accounted for record 28.4% of its population in 2018",
        "url": "https://www.youtube.com/watch?v=AWhhlqXvxUQ",
        "duration": 44.0,
        "channel": "Arirang News"
      },
      {
        "title": "Japan Is Changing How We'll Grow Old (360 Video)",
        "url": "https://www.youtube.com/watch?v=zahhBhg2z-Q",
        "duration": 287.0,
        "channel": "The Wall Street Journal"
      },
      {
        "title": "Coping With A Super-Ageing Nation | Deciphering Japan | Episode 3/4",
        "url": "https://www.youtube.com/watch?v=HQU-NeP_spU",
        "duration": 2685.0,
        "channel": "CNA Insider"
      }
    ]
  }
]
